logicplum/__init__.py
logicplum/config.py
logicplum/credential.py
logicplum/logicplum.py
logicplum/project.py
logicplum-1.0.1.dist-info/LICENCE
logicplum-1.0.1.dist-info/METADATA
logicplum-1.0.1.dist-info/WHEEL
logicplum-1.0.1.dist-info/entry_points.txt
logicplum-1.0.1.dist-info/top_level.txt
logicplum-1.0.1.dist-info/RECORD
