Metadata-Version: 2.1
Name: logicplum
Version: 1.0.1
Summary: This client library is designed to support the LogicPlum API.
Home-page: https://github.com/LogicPlum/logicplum_v3
Author: LogicPlum, Inc.
Author-email: message@logicplum.com
License: MIT
Keywords: logicplum machine-learning AI automl prediction model
Platform: UNKNOWN
Classifier: Development Status :: 4 - Beta
Classifier: Programming Language :: Python :: 3
Classifier: License :: OSI Approved :: MIT License
Classifier: Operating System :: OS Independent
Classifier: Topic :: Scientific/Engineering :: Artificial Intelligence
Requires-Python: >=3.6
Requires-Dist: pandas (>=1.2.1)
Requires-Dist: PyYAML (>=5.4.1)
Requires-Dist: requests (>=2.25.1)
Requires-Dist: twine (>=3.3.0)
